agentai/__init__.py
agentai/client.py
agentai/exceptions.py
agentai-0.1.3.dist-info/licenses/LICENSE
agentai-0.1.3.dist-info/METADATA
agentai-0.1.3.dist-info/WHEEL
agentai-0.1.3.dist-info/top_level.txt
agentai-0.1.3.dist-info/RECORD
