Metadata-Version: 2.4
Name: agentai
Version: 0.1.3
Summary: A Python client for the Agent.ai API
Home-page: https://github.com/OnStartups/python_sdk
Author: Andrei Oprisan
Author-email: andrei@agent.ai
Project-URL: Documentation, https://github.com/OnStartups/python_sdk#readme
Project-URL: Bug Tracker, https://github.com/OnStartups/python_sdk/issues
Keywords: agent.ai,ai,llm,api,client,chatbot,automation
Classifier: Development Status :: 4 - Beta
Classifier: Intended Audience :: Developers
Classifier: Programming Language :: Python :: 3
Classifier: Programming Language :: Python :: 3.8
Classifier: Programming Language :: Python :: 3.9
Classifier: Programming Language :: Python :: 3.10
Classifier: Programming Language :: Python :: 3.11
Classifier: Programming Language :: Python :: 3.12
Classifier: License :: OSI Approved :: MIT License
Classifier: Operating System :: OS Independent
Requires-Python: >=3.8
License-File: LICENSE
Requires-Dist: requests>=2.25.0
Dynamic: author
Dynamic: author-email
Dynamic: classifier
Dynamic: description
Dynamic: description-content-type
Dynamic: home-page
Dynamic: keywords
Dynamic: license-file
Dynamic: project-url
Dynamic: requires-dist
Dynamic: requires-python
Dynamic: summary
